<?xml version="1.0" encoding="utf-8" ?><dwsync><file name="background.jpg" server="ftp.modwest.com//htdocs/beta/" local="3443206976" remote="318763443836103488" Dst="-1" /><file name="favicon.ico" server="ftp.modwest.com//htdocs/beta/" local="3449955907" remote="318763443842852505" Dst="-1" /><file name="logo3.png" server="ftp.modwest.com//htdocs/beta/" local="3443206976" remote="318763443836103488" Dst="-1" /><file name="delete.png" server="ftp.modwest.com//htdocs/beta/" local="3443206976" remote="318763443836103488" Dst="-1" /><file name="loading.gif" server="ftp.modwest.com//htdocs/beta/" local="3443206976" remote="318763443836103488" Dst="-1" /><file name="backarrow.png" server="ftp.modwest.com//htdocs/beta/" local="3449702961" remote="318763443842599488" Dst="-1" /><file name="loadingcircle.gif" server="ftp.modwest.com//htdocs/beta/" local="3443206976" remote="318763443836103488" Dst="-1" /><file name="background.png" server="ftp.modwest.com//htdocs/beta/" local="3449095472" remote="318763443842580960" Dst="-1" /><file name="logo2.png" server="ftp.modwest.com//htdocs/beta/" local="3428079684" remote="318763443837933038" Dst="-1" /><file name="test1.png" server="ftp.modwest.com//htdocs/beta/" local="3428079684" remote="318763443837933038" Dst="-1" /><file name="test2.png" server="ftp.modwest.com//htdocs/beta/" local="3428079686" remote="318763443837933039" Dst="-1" /><file name="backarrow.png" server="ftp.modwest.com//htdocs/www/" local="3449702961" remote="318763443843620774" Dst="-1" /><file name="background.jpg" server="ftp.modwest.com//htdocs/www/" local="3443206976" remote="318763443837933894" Dst="-1" /><file name="background.png" server="ftp.modwest.com//htdocs/www/" local="3449095472" remote="318763443843620777" Dst="-1" /><file name="delete.png" server="ftp.modwest.com//htdocs/www/" local="3443206976" remote="318763443837933896" Dst="-1" /><file name="favicon.ico" server="ftp.modwest.com//htdocs/www/" local="3449955907" remote="318763443843620782" Dst="-1" /><file name="loading.gif" server="ftp.modwest.com//htdocs/www/" local="3443206976" remote="318763443837933898" Dst="-1" /><file name="loadingcircle.gif" server="ftp.modwest.com//htdocs/www/" local="3443206976" remote="318763443837933899" Dst="-1" /><file name="logo2.png" server="ftp.modwest.com//htdocs/www/" local="3428079684" remote="318763443837933900" Dst="-1" /><file name="logo3.png" server="ftp.modwest.com//htdocs/www/" local="3443206976" remote="318763443837933902" Dst="-1" /><file name="test1.png" server="ftp.modwest.com//htdocs/www/" local="3428079684" remote="318763443837933907" Dst="-1" /><file name="test2.png" server="ftp.modwest.com//htdocs/www/" local="3428079686" remote="318763443837933908" Dst="-1" /><file name="agency.png" server="ftp.modwest.com//htdocs/www/" local="3428613956" remote="318763443839119965" Dst="-1" /><file name="hosting.png" server="ftp.modwest.com//htdocs/www/" local="3428613956" remote="318763443839119970" Dst="-1" /><file name="lock.png" server="ftp.modwest.com//htdocs/www/" local="3428613958" remote="318763443839119972" Dst="-1" /><file name="logo4.png" server="ftp.modwest.com//htdocs/www/" local="3428399312" remote="318763443839119975" Dst="-1" /><file name="question.png" server="ftp.modwest.com//htdocs/www/" local="3430433562" remote="318763443839119976" Dst="-1" /><file name="slide1.png" server="ftp.modwest.com//htdocs/www/" local="3428349040" remote="318763443839119977" Dst="-1" /><file name="slide2.png" server="ftp.modwest.com//htdocs/www/" local="3428349042" remote="318763443839119978" Dst="-1" /><file name="slide3.png" server="ftp.modwest.com//htdocs/www/" local="3428349042" remote="318763443839119978" Dst="-1" /><file name="update.png" server="ftp.modwest.com//htdocs/www/" local="3430158986" remote="318763443839120000" Dst="-1" /><file name="border.png" server="ftp.modwest.com//htdocs/beta/" local="3449090855" remote="318763443842580972" Dst="-1" /><file name="logo5.png" server="ftp.modwest.com//htdocs/beta/" local="3449093981" remote="318763443842580976" Dst="-1" /><file name="icon1.png" server="ftp.modwest.com//htdocs/beta/" local="3449921667" remote="318763443842818197" Dst="-1" /><file name="border2.png" server="ftp.modwest.com//htdocs/beta/" local="3450021868" remote="318763443842918385" Dst="-1" /><file name=".DS_Store" server="ftp.modwest.com//htdocs/www/" local="3450021707" remote="318763443843620771" Dst="-1" /><file name="backarrow.psd" server="ftp.modwest.com//htdocs/www/" local="3449702944" remote="318763443843620774" Dst="-1" /><file name="border.png" server="ftp.modwest.com//htdocs/www/" local="3449090855" remote="318763443843620778" Dst="-1" /><file name="border2.png" server="ftp.modwest.com//htdocs/www/" local="3450021868" remote="318763443843620779" Dst="-1" /><file name="border2.psd" server="ftp.modwest.com//htdocs/www/" local="3450374092" remote="318763443843620780" Dst="-1" /><file name="favicon.png" server="ftp.modwest.com//htdocs/www/" local="3449955757" remote="318763443843620782" Dst="-1" /><file name="favicon.psd" server="ftp.modwest.com//htdocs/www/" local="3449955754" remote="318763443843620783" Dst="-1" /><file name="icon1.png" server="ftp.modwest.com//htdocs/www/" local="3449921667" remote="318763443843620785" Dst="-1" /><file name="icon1.psd" server="ftp.modwest.com//htdocs/www/" local="3449921661" remote="318763443843620786" Dst="-1" /><file name="logo5.png" server="ftp.modwest.com//htdocs/www/" local="3449093981" remote="318763443843620790" Dst="-1" /></dwsync>